README.md
setup.py
gfapi_cffi/__init__.py
gfapi_cffi/exceptions.py
gfapi_cffi/gfapi.py
gfapi_cffi/utils.py
gfapi_cffi.egg-info/PKG-INFO
gfapi_cffi.egg-info/SOURCES.txt
gfapi_cffi.egg-info/dependency_links.txt
gfapi_cffi.egg-info/requires.txt
gfapi_cffi.egg-info/top_level.txt
gfapi_cffi/libgfapi/__init__.py
gfapi_cffi/libgfapi/build_cffi_libgfapi.py