Metadata-Version: 2.1
Name: gfapi-cffi
Version: 0.1.0
Summary: Python bindings for GlusterFS libgfapi by CFFI
Home-page: http://www.gluster.org
Author: AiPods
Author-email: aihd-cqu@foxmail.com
License: GPLv2 or LGPLv3+
Classifier: Development Status :: 5 - Production/Stable
Classifier: Intended Audience :: Developers
Classifier: License :: OSI Approved :: GNU Lesser General Public License v3 or later (LGPLv3+)
Classifier: License :: OSI Approved :: GNU General Public License v2 (GPLv2)
Classifier: Operating System :: POSIX :: Linux
Classifier: Programming Language :: Python
Classifier: Programming Language :: Python :: 3
Classifier: Topic :: System :: Filesystems
Requires-Python: >=3
Requires-Dist: cffi>=1.10.0
